README.md
setup.py
vtemplate/__init__.py
vtemplate/vtemplate.py
vtemplate.egg-info/PKG-INFO
vtemplate.egg-info/SOURCES.txt
vtemplate.egg-info/dependency_links.txt
vtemplate.egg-info/top_level.txt