Metadata-Version: 2.1
Name: vtemplate
Version: 0.0.2
Summary: A package to create the project directories in a structure
Home-page: https://github.com/frier-sam/vtemplate
Author: sam-iau
Author-email: sam-iau@outlook.com
License: UNKNOWN
Platform: UNKNOWN
Classifier: Programming Language :: Python :: 3.6
Classifier: License :: OSI Approved :: MIT License
Classifier: Operating System :: OS Independent
